pyholaclient/__init__.py
pyholaclient/pyholaclient.py
pyholaclient/Classes/coupon.py
pyholaclient/Classes/package.py
pyholaclient/Classes/sysinfo.py
pyholaclient/Classes/user.py
pyholaclient-1.1.4.dist-info/LICENSE
pyholaclient-1.1.4.dist-info/METADATA
pyholaclient-1.1.4.dist-info/WHEEL
pyholaclient-1.1.4.dist-info/top_level.txt
pyholaclient-1.1.4.dist-info/RECORD
